MANIFEST.in
setup.py
bootstrap_toolkit/__init__.py
bootstrap_toolkit/_version.py
bootstrap_toolkit/widgets.py
bootstrap_toolkit/static/bootstrap_toolkit/js/init_datepicker.js
bootstrap_toolkit/static/datepicker/css/datepicker.css
bootstrap_toolkit/static/datepicker/js/bootstrap-datepicker.js
bootstrap_toolkit/static/datepicker/js/locales/bootstrap-datepicker.ar.js
bootstrap_toolkit/static/datepicker/js/locales/bootstrap-datepicker.bg.js
bootstrap_toolkit/static/datepicker/js/locales/bootstrap-datepicker.ca.js
bootstrap_toolkit/static/datepicker/js/locales/bootstrap-datepicker.cs.js
bootstrap_toolkit/static/datepicker/js/locales/bootstrap-datepicker.da.js
bootstrap_toolkit/static/datepicker/js/locales/bootstrap-datepicker.de.js
bootstrap_toolkit/static/datepicker/js/locales/bootstrap-datepicker.el.js
bootstrap_toolkit/static/datepicker/js/locales/bootstrap-datepicker.es.js
bootstrap_toolkit/static/datepicker/js/locales/bootstrap-datepicker.et.js
bootstrap_toolkit/static/datepicker/js/locales/bootstrap-datepicker.fi.js
bootstrap_toolkit/static/datepicker/js/locales/bootstrap-datepicker.fr.js
bootstrap_toolkit/static/datepicker/js/locales/bootstrap-datepicker.he.js
bootstrap_toolkit/static/datepicker/js/locales/bootstrap-datepicker.hr.js
bootstrap_toolkit/static/datepicker/js/locales/bootstrap-datepicker.hu.js
bootstrap_toolkit/static/datepicker/js/locales/bootstrap-datepicker.id.js
bootstrap_toolkit/static/datepicker/js/locales/bootstrap-datepicker.is.js
bootstrap_toolkit/static/datepicker/js/locales/bootstrap-datepicker.it.js
bootstrap_toolkit/static/datepicker/js/locales/bootstrap-datepicker.ja.js
bootstrap_toolkit/static/datepicker/js/locales/bootstrap-datepicker.kr.js
bootstrap_toolkit/static/datepicker/js/locales/bootstrap-datepicker.lt.js
bootstrap_toolkit/static/datepicker/js/locales/bootstrap-datepicker.lv.js
bootstrap_toolkit/static/datepicker/js/locales/bootstrap-datepicker.mk.js
bootstrap_toolkit/static/datepicker/js/locales/bootstrap-datepicker.ms.js
django_bootstrap_toolkit.egg-info/PKG-INFO
django_bootstrap_toolkit.egg-info/SOURCES.txt
django_bootstrap_toolkit.egg-info/dependency_links.txt
django_bootstrap_toolkit.egg-info/top_level.txt