Metadata-Version: 1.0
Name: django-bootstrap-toolkit
Version: 2.14.0
Summary: Bootstrap support for Django projects
Home-page: https://github.com/dyve/django-bootstrap-toolkit
Author: Dylan Verheul
Author-email: dylan@dyve.net
License: Apache License 2.0
Platform: UNKNOWN
Classifier: Development Status :: 5 - Production/Stable
Classifier: Intended Audience :: Developers
Classifier: License :: OSI Approved :: Apache Software License
Classifier: Programming Language :: Python
Classifier: Operating System :: OS Independent
Classifier: Topic :: Software Development :: Libraries
Classifier: Topic :: Utilities
Classifier: Environment :: Web Environment
Classifier: Framework :: Django
